{"name":"fastcgi","slug":"fastcgi","count":1,"postlist":[{"title":"SSRF之攻击fastcgi","uid":"8248c77bcf89d80dbace562f19312a67","slug":"SSRF之攻击fastcgi","date":"2023-04-16T08:08:10.000Z","updated":"2023-04-16T08:10:26.162Z","comments":true,"path":"api/articles/SSRF之攻击fastcgi.json","keywords":null,"cover":"https://blog-1313934826.cos.ap-chengdu.myqcloud.com/blog-images/18.jpeg","text":"这篇文章介绍fastcgi的攻击方式。 ssrf之攻击fastcgi1.了解CGI、FastCGI、PHP-FPM我们知道，在网站架构中，Web Server（如Nginx）只是内容的分发者 当客户端请求的是index.php，根据配置文件Web Server辨别不是静态文件，此...","link":"","photos":[],"count_time":{"symbolsCount":"7.5k","symbolsTime":"7 mins."},"categories":[{"name":"SSRF","slug":"SSRF","count":1,"path":"api/categories/SSRF.json"}],"tags":[{"name":"websec","slug":"websec","count":19,"path":"api/tags/websec.json"},{"name":"fastcgi","slug":"fastcgi","count":1,"path":"api/tags/fastcgi.json"},{"name":"SSRF","slug":"SSRF","count":2,"path":"api/tags/SSRF.json"}],"author":{"name":"uf9n1x","slug":"blog-author","avatar":"https://blog-1313934826.cos.ap-chengdu.myqcloud.com/blog-images/avator3.JPG","link":"/","description":"守护我最爱的大苹果！！！","socials":{"github":"https://github.com/uf9n1x","twitter":"","stackoverflow":"","wechat":"","qq":"","weibo":"","zhihu":"","csdn":"https://www.cnblogs.com/uf9n1x/","juejin":"","customs":{}}},"feature":false}]}